README.md
makerc.py
setup.py
cmaker/__init__.py
cmaker/compiler.py
cmaker/config.py
cmaker/dcentral.py
cmaker/dfile.py
cmaker/fcentral.py
cmaker/maker.py
cmaker/mfile.py
cmaker/srcfile.py
cmaker.egg-info/PKG-INFO
cmaker.egg-info/SOURCES.txt
cmaker.egg-info/dependency_links.txt
cmaker.egg-info/top_level.txt