Metadata-Version: 2.1
Name: cmaker
Version: 0.0.5
Summary: Recursive make-operation for sprawling C++ projects.
Home-page: https://github.com/ychnlgy/Cmaker
Author: Yuchen Li
Author-email: ychnlgy@gmail.com
License: MIT
Platform: UNKNOWN
